rdflib_django/__init__.py
rdflib_django/admin.py
rdflib_django/apps.py
rdflib_django/fields.py
rdflib_django/forms.py
rdflib_django/management/__init__.py
rdflib_django/management/commands/__init__.py
rdflib_django/management/commands/rdf_export.py
rdflib_django/management/commands/rdf_import.py
rdflib_django/migrations/0001_initial.py
rdflib_django/migrations/0002_auto_20181112_1317.py
rdflib_django/migrations/0003_alter_namedgraph_id_alter_namespacemodel_id_and_more.py
rdflib_django/migrations/__init__.py
rdflib_django/models.py
rdflib_django/store.py
rdflib_django/utils.py
rdflib_django3-0.4.1.dist-info/LICENSE
rdflib_django3-0.4.1.dist-info/LICENSE.publysher
rdflib_django3-0.4.1.dist-info/METADATA
rdflib_django3-0.4.1.dist-info/WHEEL
rdflib_django3-0.4.1.dist-info/entry_points.txt
rdflib_django3-0.4.1.dist-info/RECORD
