Metadata-Version: 2.1
Name: rdflib-django3
Version: 0.4.1
Summary: Store implementation for RDFlib using Django models as its backend (fork)
Home-page: http://github.com/devkral/rdflib-django3
License: MIT
Author: Alexander K
Author-email: devkral@web.de
Requires-Python: >=3.9,<4.0
Classifier: Development Status :: 3 - Alpha
Classifier: Framework :: Django
Classifier: Intended Audience :: Developers
Classifier: License :: OSI Approved :: MIT License
Classifier: Operating System :: OS Independent
Classifier: Programming Language :: Python
Classifier: Programming Language :: Python :: 3
Classifier: Programming Language :: Python :: 3.9
Classifier: Programming Language :: Python :: 3.10
Classifier: Programming Language :: Python :: 3.11
Classifier: Programming Language :: Python :: 3.12
Classifier: Topic :: Internet :: WWW/HTTP
Classifier: Topic :: Software Development :: Libraries :: Python Modules
Requires-Dist: django (>=3.0)
Requires-Dist: rdflib (>=3.2.1)
Project-URL: Repository, http://github.com/devkral/rdflib-django3
